shinkei/__init__.py
shinkei/__init__.pyi
shinkei/api.py
shinkei/api.pyi
shinkei/backoff.py
shinkei/backoff.pyi
shinkei/client.py
shinkei/client.pyi
shinkei/exceptions.py
shinkei/exceptions.pyi
shinkei/gateway.py
shinkei/gateway.pyi
shinkei/handlers.py
shinkei/handlers.pyi
shinkei/iterators.py
shinkei/iterators.pyi
shinkei/keepalive.py
shinkei/keepalive.pyi
shinkei/objects.py
shinkei/objects.pyi
shinkei/querybuilder.py
shinkei/querybuilder.pyi
shinkei/ext/__init__.py
shinkei/ext/__init__.pyi
shinkei/ext/bot.py
shinkei/ext/bot.pyi
shinkei-0.1.6.dist-info/LICENSE
shinkei-0.1.6.dist-info/METADATA
shinkei-0.1.6.dist-info/WHEEL
shinkei-0.1.6.dist-info/top_level.txt
shinkei-0.1.6.dist-info/RECORD
