Metadata-Version: 2.1
Name: shinkei
Version: 0.1.6
Summary: An asynchronous client for singyeong
Home-page: https://github.com/PendragonLore/shinkei
Author: Lorenzo
License: MIT
Project-URL: Code, https://github.com/PendragonLore/shinkei
Project-URL: Issue tracker, https://github.com/PendragonLore/shinkei/issues
Project-URL: Documentation, https://shinkei.rtfd.io
Keywords: ipc,asyncio,singyeong,discord
Platform: any
Classifier: License :: OSI Approved :: MIT License
Classifier: Framework :: AsyncIO
Classifier: Programming Language :: Python :: 3 :: Only
Classifier: Programming Language :: Python :: 3.5
Classifier: Programming Language :: Python :: 3.6
Classifier: Programming Language :: Python :: 3.7
Classifier: Programming Language :: Python :: Implementation :: CPython
Classifier: Development Status :: 3 - Alpha
Classifier: Natural Language :: English
Classifier: Intended Audience :: Developers
Classifier: Operating System :: OS Independent
Classifier: Topic :: Internet
Classifier: Topic :: Utilities
Classifier: Topic :: System :: Networking
Classifier: Topic :: Software Development :: Libraries
Requires-Python: >=3.5.3
Requires-Dist: aiohttp (<3.6.0,>=3.3.0)
Requires-Dist: websockets (<7.0,>=6.0)
Provides-Extra: docs
Requires-Dist: sphinx ; extra == 'docs'
Requires-Dist: sphinxcontrib-trio ; extra == 'docs'
Provides-Extra: tests
Requires-Dist: pytest ; extra == 'tests'
Requires-Dist: flake8 ; extra == 'tests'
Requires-Dist: isort ; extra == 'tests'
Requires-Dist: mypy ; extra == 'tests'
Requires-Dist: pydocstyle ; extra == 'tests'
Provides-Extra: ujson
Requires-Dist: ujson ; extra == 'ujson'
